dev_achievements/__init__.py
dev_achievements/achievements.py
dev_achievements/processing/__init__.py
dev_achievements/processing/tree.py
dev_achievements/processing/visitor.py
dev_achievements/utilities/__init__.py
dev_achievements/utilities/constants.py
dev_achievements/utilities/utils.py
dev_achievements-1.0.3.dist-info/LICENSE
dev_achievements-1.0.3.dist-info/METADATA
dev_achievements-1.0.3.dist-info/WHEEL
dev_achievements-1.0.3.dist-info/top_level.txt
dev_achievements-1.0.3.dist-info/RECORD
