Metadata-Version: 2.1
Name: dev-achievements
Version: 1.0.3
Summary: Earn Achievements while learning how to code
Home-page: https://github.com/raviolliii/dev-achievements
Author: Ravi Patel
Author-email: ravi.patel1245@gmail.com
License: UNKNOWN
Platform: UNKNOWN
Classifier: Programming Language :: Python :: 3
Classifier: License :: OSI Approved :: MIT License
Classifier: Operating System :: OS Independent
Requires-Python: >=3.5
